tiksing/__init__.py
tiksing-0.0.2.dist-info/LICENSE
tiksing-0.0.2.dist-info/METADATA
tiksing-0.0.2.dist-info/WHEEL
tiksing-0.0.2.dist-info/top_level.txt
tiksing-0.0.2.dist-info/RECORD
